info_serie_tv/__init__.py
info_serie_tv/info_serie_tv.py
info_serie_tv-1.0.0.1.dist-info/LICENSE
info_serie_tv-1.0.0.1.dist-info/METADATA
info_serie_tv-1.0.0.1.dist-info/WHEEL
info_serie_tv-1.0.0.1.dist-info/entry_points.txt
info_serie_tv-1.0.0.1.dist-info/top_level.txt
info_serie_tv-1.0.0.1.dist-info/RECORD
