Metadata-Version: 2.1
Name: info-serie-tv
Version: 1.0.0.1
Summary: SerieTvItaly_bot API
Home-page: https://github.com/KingKaitoKid/info_serie_tv
Author: King Kaito Kid
Author-email: djstrix@me.com
License: UNKNOWN
Platform: UNKNOWN
Classifier: Programming Language :: Python :: 3
Classifier: License :: OSI Approved :: MIT License
Classifier: Operating System :: OS Independent
Requires-Python: >=3.6
Requires-Dist: requests
